pydiction/__init__.py
pydiction/core.py
pydiction/operators.py
pydiction/py.typed
pydiction/utils.py
pydiction-0.1.0.dist-info/LICENSE
pydiction-0.1.0.dist-info/METADATA
pydiction-0.1.0.dist-info/WHEEL
pydiction-0.1.0.dist-info/RECORD
